LICENSE
MANIFEST.in
README.md
pyproject.toml
setup.py
bindings/cpp/main.cpp
bindings/cpp/utils.cpp
bindings/cpp/wapper.cpp
bindings/includes/pairhash.hpp
bindings/includes/tokenizer.hpp
bindings/includes/utils.hpp
src/shatokenizer/__init__.py
src/shatokenizer/tokenizer.py
src/shatokenizer.egg-info/PKG-INFO
src/shatokenizer.egg-info/SOURCES.txt
src/shatokenizer.egg-info/dependency_links.txt
src/shatokenizer.egg-info/not-zip-safe
src/shatokenizer.egg-info/requires.txt
src/shatokenizer.egg-info/top_level.txt