Metadata-Version: 2.4
Name: shatokenizer
Version: 0.1.0
Summary: High-performance bpe tokenizer with C++ backend and Python bindings
Home-page: https://github.com/shaheen-coder/shatokenizer
Author: Shaheen Ahmed
Author-email: shaheenvsa@gmail.com
Classifier: Programming Language :: Python :: 3
Classifier: Programming Language :: C++
Classifier: License :: OSI Approved :: MIT License
Classifier: Operating System :: OS Independent
Requires-Python: >=3.7
License-File: LICENSE
Requires-Dist: pybind11>=2.6.0
Dynamic: author
Dynamic: author-email
Dynamic: classifier
Dynamic: description
Dynamic: description-content-type
Dynamic: home-page
Dynamic: license-file
Dynamic: requires-dist
Dynamic: requires-python
Dynamic: summary
